shakemap_modules/base/base.py
shakemap_modules/base/cli.py
shakemap_modules/base/transfer_base.py
shakemap_modules/coremods/assemble.py
shakemap_modules/coremods/associate.py
shakemap_modules/coremods/augment.py
shakemap_modules/coremods/contour.py
shakemap_modules/coremods/coverage.py
shakemap_modules/coremods/dyfi.py
shakemap_modules/coremods/exception.py
shakemap_modules/coremods/gridxml.py
shakemap_modules/coremods/history.py
shakemap_modules/coremods/info.py
shakemap_modules/coremods/kml.py
shakemap_modules/coremods/makecsv.py
shakemap_modules/coremods/mapping.py
shakemap_modules/coremods/model.py
shakemap_modules/coremods/plotregr.py
shakemap_modules/coremods/raster.py
shakemap_modules/coremods/rupture.py
shakemap_modules/coremods/save.py
shakemap_modules/coremods/shape.py
shakemap_modules/coremods/sleep.py
shakemap_modules/coremods/sm_select.py
shakemap_modules/coremods/stations.py
shakemap_modules/coremods/transfer_email.py
shakemap_modules/coremods/transfer_pdl.py
shakemap_modules/coremods/transfer_scp.py
shakemap_modules/coremods/uncertaintymaps.py
shakemap_modules/coremods/xtestimage.py
shakemap_modules/coremods/xtestplot.py
shakemap_modules/coremods/xtestplot_multi.py
shakemap_modules/coremods/xtestplot_spectra.py
shakemap_modules/data/fdsn_networks.json
shakemap_modules/data/gmpe_sets.conf
shakemap_modules/data/logging.conf
shakemap_modules/data/loggingspec.conf
shakemap_modules/data/migrate.conf
shakemap_modules/data/migratespec.conf
shakemap_modules/data/model.conf
shakemap_modules/data/modelspec.conf
shakemap_modules/data/modules.conf
shakemap_modules/data/modulesspec.conf
shakemap_modules/data/products.conf
shakemap_modules/data/productsspec.conf
shakemap_modules/data/queue.conf
shakemap_modules/data/queuespec.conf
shakemap_modules/data/select.conf
shakemap_modules/data/selectspec.conf
shakemap_modules/data/shake.conf
shakemap_modules/data/shakespec.conf
shakemap_modules/data/simulationspec.conf
shakemap_modules/data/transfer.conf
shakemap_modules-1.1.15.dist-info/licenses/LICENSE.md
shakemap_modules-1.1.15.dist-info/METADATA
shakemap_modules-1.1.15.dist-info/WHEEL
shakemap_modules-1.1.15.dist-info/entry_points.txt
shakemap_modules-1.1.15.dist-info/top_level.txt
shakemap_modules-1.1.15.dist-info/RECORD
